<?xml version="1.0" encoding="UTF-8"?>
<objects serializationModel="Studio.01.08.00">
    <object class="Event" id="{b487bf4e-e328-4c40-8050-3cd3787d92bf}">
        <property name="name">
            <value>OPEN</value>
        </property>
        <property name="outputFormat">
            <value>2</value>
        </property>
        <relationship name="mixer">
            <destination>{d29fcada-314e-4969-8b92-770ef9d73fff}</destination>
        </relationship>
        <relationship name="masterTrack">
            <destination>{d16afc20-2cc8-4246-beac-05cf43d35a2c}</destination>
        </relationship>
        <relationship name="mixerInput">
            <destination>{08ff97bb-6657-4d99-8cee-48c57a965871}</destination>
        </relationship>
        <relationship name="automatableProperties">
            <destination>{21c84428-8ec1-4dea-a2b2-cb04a88ac7f8}</destination>
        </relationship>
        <relationship name="markerTracks">
            <destination>{db4ceb62-6ac8-4f85-9f84-769e8c42204a}</destination>
        </relationship>
        <relationship name="groupTracks">
            <destination>{9d3e0783-87e5-47f9-9be6-73b54865e2b6}</destination>
            <destination>{d75abb48-677c-4544-b6c9-38946972eae4}</destination>
            <destination>{4363e3b3-6a3c-450c-843a-23cc27d042c9}</destination>
            <destination>{9a7d08c8-cad4-49b1-af0c-402217e36551}</destination>
            <destination>{c5b7623f-734f-40d8-8685-ae8cb3b03f57}</destination>
        </relationship>
        <relationship name="timeline">
            <destination>{454a6d0e-a517-4d81-ba7c-4f0ae46381f5}</destination>
        </relationship>
        <relationship name="banks">
            <destination>{8203f363-f514-4315-9eff-45e8af3a9822}</destination>
        </relationship>
        <relationship name="folder">
            <destination>{846b5efe-bb97-46d0-9fe4-fb04377554ec}</destination>
        </relationship>
    </object>
    <object class="EventMixer" id="{d29fcada-314e-4969-8b92-770ef9d73fff}">
        <relationship name="masterBus">
            <destination>{646b187d-8544-46c6-b46f-ba1730cac754}</destination>
        </relationship>
    </object>
    <object class="MasterTrack" id="{d16afc20-2cc8-4246-beac-05cf43d35a2c}">
        <relationship name="mixerGroup">
            <destination>{646b187d-8544-46c6-b46f-ba1730cac754}</destination>
        </relationship>
    </object>
    <object class="MixerInput" id="{08ff97bb-6657-4d99-8cee-48c57a965871}">
        <relationship name="effectChain">
            <destination>{a541f718-892e-45ee-bbdf-f8e4ab1b60a0}</destination>
        </relationship>
        <relationship name="panner">
            <destination>{00ecbd4d-6e59-4ffd-a046-17926a3ba577}</destination>
        </relationship>
        <relationship name="output">
            <destination>{6435d82b-8995-4913-80bd-e613b168e091}</destination>
        </relationship>
    </object>
    <object class="EventAutomatableProperties" id="{21c84428-8ec1-4dea-a2b2-cb04a88ac7f8}"/>
    <object class="MarkerTrack" id="{db4ceb62-6ac8-4f85-9f84-769e8c42204a}"/>
    <object class="GroupTrack" id="{9d3e0783-87e5-47f9-9be6-73b54865e2b6}">
        <relationship name="modules">
            <destination>{76aceb6c-f336-456f-851d-f9a69510ed8f}</destination>
        </relationship>
        <relationship name="mixerGroup">
            <destination>{3208085f-5732-4396-84ed-5b2de287bbe0}</destination>
        </relationship>
    </object>
    <object class="GroupTrack" id="{d75abb48-677c-4544-b6c9-38946972eae4}">
        <relationship name="modules">
            <destination>{e5dd1313-f517-47eb-b96c-a4131712dc92}</destination>
        </relationship>
        <relationship name="mixerGroup">
            <destination>{86c80f40-8707-4c54-be52-e196c5130166}</destination>
        </relationship>
    </object>
    <object class="GroupTrack" id="{4363e3b3-6a3c-450c-843a-23cc27d042c9}">
        <relationship name="mixerGroup">
            <destination>{43f11008-d88a-4783-b13a-0b3deb64941d}</destination>
        </relationship>
    </object>
    <object class="GroupTrack" id="{9a7d08c8-cad4-49b1-af0c-402217e36551}">
        <relationship name="modules">
            <destination>{04130706-5e7a-430d-b983-95987d7b1e76}</destination>
        </relationship>
        <relationship name="mixerGroup">
            <destination>{1d52997a-6870-44b3-9e5a-88aa843d1d2f}</destination>
        </relationship>
    </object>
    <object class="GroupTrack" id="{c5b7623f-734f-40d8-8685-ae8cb3b03f57}">
        <relationship name="modules">
            <destination>{b32a3844-d701-40f0-9467-c4080fa50c50}</destination>
        </relationship>
        <relationship name="mixerGroup">
            <destination>{80bef583-d038-4ad4-8684-83f1c396e9f7}</destination>
        </relationship>
    </object>
    <object class="Timeline" id="{454a6d0e-a517-4d81-ba7c-4f0ae46381f5}">
        <relationship name="modules">
            <destination>{76aceb6c-f336-456f-851d-f9a69510ed8f}</destination>
            <destination>{e5dd1313-f517-47eb-b96c-a4131712dc92}</destination>
            <destination>{04130706-5e7a-430d-b983-95987d7b1e76}</destination>
            <destination>{b32a3844-d701-40f0-9467-c4080fa50c50}</destination>
        </relationship>
    </object>
    <object class="EventMixerMaster" id="{646b187d-8544-46c6-b46f-ba1730cac754}">
        <property name="volume">
            <value>5</value>
        </property>
        <relationship name="effectChain">
            <destination>{34c6fc49-e252-46e3-87d1-faf61a45efe1}</destination>
        </relationship>
        <relationship name="panner">
            <destination>{3685016d-9c48-4773-938e-efc70f47008a}</destination>
        </relationship>
        <relationship name="mixer">
            <destination>{d29fcada-314e-4969-8b92-770ef9d73fff}</destination>
        </relationship>
    </object>
    <object class="MixerBusEffectChain" id="{a541f718-892e-45ee-bbdf-f8e4ab1b60a0}">
        <relationship name="effects">
            <destination>{a91be1a6-eb68-485b-97e1-d1c44f5edc80}</destination>
        </relationship>
    </object>
    <object class="MixerBusPanner" id="{00ecbd4d-6e59-4ffd-a046-17926a3ba577}"/>
    <object class="SingleSound" id="{76aceb6c-f336-456f-851d-f9a69510ed8f}">
        <property name="start">
            <value>0.30000000000000004</value>
        </property>
        <property name="length">
            <value>3.0499999999999998</value>
        </property>
        <property name="timelockedOffset">
            <value>0.70000000000000007</value>
        </property>
        <relationship name="audioFile">
            <destination>{b0c35b74-fd30-4054-80f5-553348c8bb0b}</destination>
        </relationship>
    </object>
    <object class="EventMixerGroup" id="{3208085f-5732-4396-84ed-5b2de287bbe0}">
        <property name="volume">
            <value>-4</value>
        </property>
        <property name="name">
            <value>Audio 1</value>
        </property>
        <relationship name="effectChain">
            <destination>{3f824251-075f-47a2-9e71-178d5e6895b4}</destination>
        </relationship>
        <relationship name="panner">
            <destination>{bbec7e69-35dc-4881-b539-20cad26aad18}</destination>
        </relationship>
        <relationship name="output">
            <destination>{646b187d-8544-46c6-b46f-ba1730cac754}</destination>
        </relationship>
    </object>
    <object class="MultiSound" id="{e5dd1313-f517-47eb-b96c-a4131712dc92}">
        <property name="start">
            <value>0.10000000000000001</value>
        </property>
        <property name="length">
            <value>0.20000000000000001</value>
        </property>
        <property name="pitch">
            <value>-1.20000005</value>
        </property>
        <property name="randomized">
            <value>false</value>
        </property>
        <relationship name="sounds">
            <destination>{bef8d682-e741-4e9f-a68c-a51d326de5d8}</destination>
            <destination>{9b29c9b4-c69e-44ef-b67d-d51554289773}</destination>
        </relationship>
    </object>
    <object class="EventMixerGroup" id="{86c80f40-8707-4c54-be52-e196c5130166}">
        <property name="volume">
            <value>-8</value>
        </property>
        <property name="name">
            <value>RATTLE</value>
        </property>
        <relationship name="effectChain">
            <destination>{283839ab-d1f7-4132-9a5a-cbaf0d9a1fd3}</destination>
        </relationship>
        <relationship name="panner">
            <destination>{d5aa28e7-4723-4b4f-83b3-5d5e9e608929}</destination>
        </relationship>
        <relationship name="output">
            <destination>{646b187d-8544-46c6-b46f-ba1730cac754}</destination>
        </relationship>
    </object>
    <object class="EventMixerGroup" id="{43f11008-d88a-4783-b13a-0b3deb64941d}">
        <property name="name">
            <value>LOCK</value>
        </property>
        <relationship name="effectChain">
            <destination>{e4906a1b-a534-427c-88a5-06e876d59d27}</destination>
        </relationship>
        <relationship name="panner">
            <destination>{3c04dc89-9b83-4ef9-b61d-0fef57b2c6bd}</destination>
        </relationship>
        <relationship name="output">
            <destination>{646b187d-8544-46c6-b46f-ba1730cac754}</destination>
        </relationship>
    </object>
    <object class="SingleSound" id="{04130706-5e7a-430d-b983-95987d7b1e76}">
        <property name="start">
            <value>0.05046090687075977</value>
        </property>
        <property name="length">
            <value>0.40000000000000002</value>
        </property>
        <relationship name="fadeOutCurve">
            <destination>{bc38dc27-2163-46d5-9ef8-b9163337f944}</destination>
        </relationship>
        <relationship name="audioFile">
            <destination>{2b6f9f9d-1819-4089-a120-3f4f0a28db9b}</destination>
        </relationship>
    </object>
    <object class="EventMixerGroup" id="{1d52997a-6870-44b3-9e5a-88aa843d1d2f}">
        <property name="name">
            <value>PEANUTRATTLE</value>
        </property>
        <relationship name="effectChain">
            <destination>{f1612205-56ca-4cb7-8a99-0789cd5a397a}</destination>
        </relationship>
        <relationship name="panner">
            <destination>{f2fbd082-fa7b-46eb-936f-e440a4711d4f}</destination>
        </relationship>
        <relationship name="output">
            <destination>{646b187d-8544-46c6-b46f-ba1730cac754}</destination>
        </relationship>
    </object>
    <object class="MultiSound" id="{b32a3844-d701-40f0-9467-c4080fa50c50}">
        <property name="start">
            <value>0.050000000000000003</value>
        </property>
        <property name="length">
            <value>0.40000000000000002</value>
        </property>
        <relationship name="fadeOutCurve">
            <destination>{7a3669f6-7233-4780-a371-de036d7fc4ef}</destination>
        </relationship>
        <relationship name="sounds">
            <destination>{fd918603-7b1a-44fb-90fa-85d2f513bba3}</destination>
            <destination>{1bd36cdd-c3ff-44d3-b853-570fd5872979}</destination>
        </relationship>
    </object>
    <object class="EventMixerGroup" id="{80bef583-d038-4ad4-8684-83f1c396e9f7}">
        <property name="name">
            <value>PEANUT</value>
        </property>
        <relationship name="effectChain">
            <destination>{90fe99d1-a7a6-4b12-a24d-9d24b80afbe2}</destination>
        </relationship>
        <relationship name="panner">
            <destination>{216d6058-1980-4537-b7bc-5d3cf0bbe5ae}</destination>
        </relationship>
        <relationship name="output">
            <destination>{646b187d-8544-46c6-b46f-ba1730cac754}</destination>
        </relationship>
    </object>
    <object class="MixerBusEffectChain" id="{34c6fc49-e252-46e3-87d1-faf61a45efe1}">
        <relationship name="effects">
            <destination>{81bf88df-3207-482d-8bc2-7336384574ab}</destination>
            <destination>{fa1c25c3-5ef1-4705-a917-f679136bfe20}</destination>
            <destination>{5858762a-4f0d-4ce7-bb11-5600f565c371}</destination>
        </relationship>
    </object>
    <object class="MixerBusPanner" id="{3685016d-9c48-4773-938e-efc70f47008a}"/>
    <object class="MixerBusFader" id="{a91be1a6-eb68-485b-97e1-d1c44f5edc80}"/>
    <object class="MixerBusEffectChain" id="{3f824251-075f-47a2-9e71-178d5e6895b4}">
        <relationship name="effects">
            <destination>{0089e281-38cd-4f28-9909-b2982c609421}</destination>
        </relationship>
    </object>
    <object class="MixerBusPanner" id="{bbec7e69-35dc-4881-b539-20cad26aad18}"/>
    <object class="SingleSound" id="{bef8d682-e741-4e9f-a68c-a51d326de5d8}">
        <relationship name="audioFile">
            <destination>{19420787-5a9d-4145-9581-a58042ecd176}</destination>
        </relationship>
    </object>
    <object class="SingleSound" id="{9b29c9b4-c69e-44ef-b67d-d51554289773}">
        <relationship name="audioFile">
            <destination>{055d0efe-b96b-4a77-9032-149bf1457beb}</destination>
        </relationship>
    </object>
    <object class="MixerBusEffectChain" id="{283839ab-d1f7-4132-9a5a-cbaf0d9a1fd3}">
        <relationship name="effects">
            <destination>{ab15b58a-42cf-45ac-9be1-8ccff3bba044}</destination>
        </relationship>
    </object>
    <object class="MixerBusPanner" id="{d5aa28e7-4723-4b4f-83b3-5d5e9e608929}"/>
    <object class="MixerBusEffectChain" id="{e4906a1b-a534-427c-88a5-06e876d59d27}">
        <relationship name="effects">
            <destination>{4aa2df91-18d9-412c-a92a-9b8254469ed2}</destination>
        </relationship>
    </object>
    <object class="MixerBusPanner" id="{3c04dc89-9b83-4ef9-b61d-0fef57b2c6bd}"/>
    <object class="FadeCurve" id="{bc38dc27-2163-46d5-9ef8-b9163337f944}">
        <relationship name="startPoint">
            <destination>{16152732-8992-4fc3-8a8b-636933f0a7a3}</destination>
        </relationship>
        <relationship name="endPoint">
            <destination>{6dd3302b-a622-4c5f-a016-9ebfaccfd326}</destination>
        </relationship>
    </object>
    <object class="MixerBusEffectChain" id="{f1612205-56ca-4cb7-8a99-0789cd5a397a}">
        <relationship name="effects">
            <destination>{9bb98ab0-4b90-4d2e-a55f-5725f5a1d979}</destination>
        </relationship>
    </object>
    <object class="MixerBusPanner" id="{f2fbd082-fa7b-46eb-936f-e440a4711d4f}"/>
    <object class="FadeCurve" id="{7a3669f6-7233-4780-a371-de036d7fc4ef}">
        <relationship name="startPoint">
            <destination>{6278410e-e670-427e-8f5d-9a349b5ff3d0}</destination>
        </relationship>
        <relationship name="endPoint">
            <destination>{d7a5d25e-f776-426b-bc35-430334f41024}</destination>
        </relationship>
    </object>
    <object class="SingleSound" id="{fd918603-7b1a-44fb-90fa-85d2f513bba3}">
        <relationship name="audioFile">
            <destination>{2b6f9f9d-1819-4089-a120-3f4f0a28db9b}</destination>
        </relationship>
    </object>
    <object class="SingleSound" id="{1bd36cdd-c3ff-44d3-b853-570fd5872979}">
        <relationship name="audioFile">
            <destination>{cdbad9cc-2cba-47cb-96a7-d65fd7722504}</destination>
        </relationship>
    </object>
    <object class="MixerBusEffectChain" id="{90fe99d1-a7a6-4b12-a24d-9d24b80afbe2}">
        <relationship name="effects">
            <destination>{526f04c3-8a5d-49a0-b266-00fa5215ddd0}</destination>
        </relationship>
    </object>
    <object class="MixerBusPanner" id="{216d6058-1980-4537-b7bc-5d3cf0bbe5ae}"/>
    <object class="MixerBusFader" id="{81bf88df-3207-482d-8bc2-7336384574ab}"/>
    <object class="SpatialiserEffect" id="{fa1c25c3-5ef1-4705-a917-f679136bfe20}"/>
    <object class="MixerSend" id="{5858762a-4f0d-4ce7-bb11-5600f565c371}">
        <property name="level">
            <value>-40</value>
        </property>
        <property name="inputFormat">
            <value>2</value>
        </property>
        <relationship name="mixerReturn">
            <destination>{e10d1d1b-979d-4496-a0a9-2116b749bb26}</destination>
        </relationship>
    </object>
    <object class="MixerBusFader" id="{0089e281-38cd-4f28-9909-b2982c609421}"/>
    <object class="MixerBusFader" id="{ab15b58a-42cf-45ac-9be1-8ccff3bba044}"/>
    <object class="MixerBusFader" id="{4aa2df91-18d9-412c-a92a-9b8254469ed2}"/>
    <object class="AutomationPoint" id="{16152732-8992-4fc3-8a8b-636933f0a7a3}">
        <property name="position">
            <value>0.15046090687075986</value>
        </property>
        <property name="value">
            <value>1</value>
        </property>
        <property name="curveShape">
            <value>-0.493519217</value>
        </property>
    </object>
    <object class="AutomationPoint" id="{6dd3302b-a622-4c5f-a016-9ebfaccfd326}">
        <property name="position">
            <value>0.45046090687075985</value>
        </property>
        <property name="value">
            <value>0</value>
        </property>
    </object>
    <object class="MixerBusFader" id="{9bb98ab0-4b90-4d2e-a55f-5725f5a1d979}"/>
    <object class="AutomationPoint" id="{6278410e-e670-427e-8f5d-9a349b5ff3d0}">
        <property name="position">
            <value>0.15000000000000005</value>
        </property>
        <property name="value">
            <value>1</value>
        </property>
        <property name="curveShape">
            <value>-0.483669996</value>
        </property>
    </object>
    <object class="AutomationPoint" id="{d7a5d25e-f776-426b-bc35-430334f41024}">
        <property name="position">
            <value>0.45000000000000007</value>
        </property>
        <property name="value">
            <value>0</value>
        </property>
    </object>
    <object class="MixerBusFader" id="{526f04c3-8a5d-49a0-b266-00fa5215ddd0}"/>
</objects>
